config/claude_desktop_config.json
docs/SDK_DEPLOYMENT_GUIDE.md
examples/advanced_usage.md
examples/basic_usage.md
main.py
src/__init__.py
src/sdk_server.py
src/tccli_service_loader.py
src/tencent_sdk_wrapper.py
tcloud_mcp-1.0.1.dist-info/METADATA
tcloud_mcp-1.0.1.dist-info/WHEEL
tcloud_mcp-1.0.1.dist-info/entry_points.txt
tcloud_mcp-1.0.1.dist-info/RECORD
