Metadata-Version: 2.4
Name: tcloud-mcp
Version: 1.0.1
Summary: Model Context Protocol server for Tencent Cloud services - interact with Tencent Cloud through natural language
Project-URL: Homepage, https://github.com/your-username/tencent-cloud-mcp
Project-URL: Repository, https://github.com/your-username/tencent-cloud-mcp
Project-URL: Documentation, https://github.com/your-username/tencent-cloud-mcp/blob/main/README.md
Project-URL: Issues, https://github.com/your-username/tencent-cloud-mcp/issues
Project-URL: Changelog, https://github.com/your-username/tencent-cloud-mcp/blob/main/CHANGELOG.md
Author-email: David <guowei1461@gmail.com>
License: MIT
Keywords: mcp,model-context-protocol,tencent-cloud
Classifier: Development Status :: 4 - Beta
Classifier: Intended Audience :: Developers
Classifier: Intended Audience :: System Administrators
Classifier: License :: OSI Approved :: MIT License
Classifier: Programming Language :: Python :: 3
Classifier: Programming Language :: Python :: 3.8
Classifier: Programming Language :: Python :: 3.9
Classifier: Programming Language :: Python :: 3.10
Classifier: Programming Language :: Python :: 3.11
Classifier: Programming Language :: Python :: 3.12
Classifier: Topic :: Communications :: Chat
Classifier: Topic :: Internet :: WWW/HTTP :: Dynamic Content
Classifier: Topic :: Scientific/Engineering :: Artificial Intelligence
Classifier: Topic :: Software Development :: Libraries :: Python Modules
Classifier: Topic :: System :: Systems Administration
Requires-Python: >=3.8
Requires-Dist: jmespath>=0.10.0
Requires-Dist: six>=1.16.0
Requires-Dist: tencentcloud-sdk-python>=3.0.1399
Provides-Extra: dev
Requires-Dist: black>=23.0; extra == 'dev'
Requires-Dist: isort>=5.12; extra == 'dev'
Requires-Dist: mypy>=1.0; extra == 'dev'
Requires-Dist: pytest-asyncio>=0.21.0; extra == 'dev'
Requires-Dist: pytest>=7.0; extra == 'dev'
